hybrid_face/__init__.py
hybrid_face/cli.py
hybrid_face/hybrid_merge.py
hybrid_face/filters/__init__.py
hybrid_face/filters/base.py
hybrid_face/filters/face_filters.py
hybrid_face/filters/global_filters.py
hybrid_face-0.1.3.dist-info/METADATA
hybrid_face-0.1.3.dist-info/WHEEL
hybrid_face-0.1.3.dist-info/entry_points.txt
hybrid_face-0.1.3.dist-info/top_level.txt
hybrid_face-0.1.3.dist-info/RECORD
