Metadata-Version: 2.1
Name: hybrid-face
Version: 0.1.3
Summary: See one face up close and another from far away!
Home-page: https://github.com/LeviBorodenko/hybrid-face
Author: Levi Borodenko
Author-email: levi.borodenko@gmail.com
License: UNKNOWN
Project-URL: Documentation, https://github.com/LeviBorodenko/hybrid-face
Platform: any
Classifier: Development Status :: 4 - Beta
Classifier: Programming Language :: Python
Requires-Python: >=3.8
Requires-Dist: importlib-metadata (>=4.0.1)
Requires-Dist: face-recognition (>=1.3.0)
Requires-Dist: numpy (>=1.20.2)
Requires-Dist: Pillow (>=8.2.0)
Requires-Dist: rich (>=10.1.0)
Provides-Extra: dev
Requires-Dist: flake8 ; extra == 'dev'
Requires-Dist: black ; extra == 'dev'
Requires-Dist: pre-commit ; extra == 'dev'
Requires-Dist: tox ; extra == 'dev'
Provides-Extra: testing
Requires-Dist: setuptools ; extra == 'testing'
Requires-Dist: pytest ; extra == 'testing'
Requires-Dist: pytest-cov ; extra == 'testing'
